{
  "('Z1', 'Z1', 'low', 'warmup', 'Z1', 'Z1', 'flat')": {
    "slow down": 9.462396388337382,
    "keep going": 2.0430680368127057,
    "accelerate": -29.946346294592143
  },
  "('Z1', 'Z2', 'low', 'warmup', 'Z1', 'Z1', 'downhill')": {
    "slow down": -50.15953226896523,
    "keep going": -430.3108722266034,
    "accelerate": -446.4089968555601
  },
  "('Z2', 'Z3', 'low', 'warmup', 'Z1', 'Z1', 'downhill')": {
    "slow down": -339.89446888848,
    "keep going": -488.00008153938626,
    "accelerate": -490.15812035269255
  },
  "('Z2', 'Z2', 'low', 'warmup', 'Z1', 'Z1', 'flat')": {
    "slow down": -206.6948113759035,
    "keep going": -460.8070918981882,
    "accelerate": -460.91428100001684
  },
  "('Z2', 'Z2', 'low', 'warmup', 'Z1', 'Z1', 'downhill')": {
    "slow down": -453.3279375871058,
    "keep going": -453.32575189029836,
    "accelerate": -489.4065296833843
  },
  "('Z2', 'Z1', 'low', 'warmup', 'Z1', 'Z1', 'flat')": {
    "slow down": -458.3519806035768,
    "keep going": -232.67311649060713,
    "accelerate": -458.60029480224796
  },
  "('Z2', 'Z2', 'low', 'warmup', 'Z1', 'Z1', 'uphill')": {
    "slow down": -388.0220142384376,
    "keep going": -451.0936139562727,
    "accelerate": -493.99618177351203
  },
  "('Z2', 'Z1', 'low', 'warmup', 'Z1', 'Z1', 'uphill')": {
    "slow down": -490.631943913995,
    "keep going": -490.7153507248075,
    "accelerate": -451.5734398971183
  },
  "('Z1', 'Z1', 'low', 'warmup', 'Z1', 'Z1', 'uphill')": {
    "slow down": 68.37481511440241,
    "keep going": -70.99984397658405,
    "accelerate": -309.2900375744323
  },
  "('Z1', 'Z2', 'low', 'warmup', 'Z1', 'Z1', 'flat')": {
    "slow down": 24.18454176748588,
    "keep going": -411.0854450227599,
    "accelerate": -439.2368506488841
  },
  "('Z2', 'Z3', 'low', 'warmup', 'Z1', 'Z1', 'uphill')": {
    "slow down": -435.9519667455934,
    "keep going": -484.5874092510011,
    "accelerate": -485.8259643029167
  },
  "('Z2', 'Z3', 'low', 'warmup', 'Z1', 'Z1', 'flat')": {
    "slow down": -478.9127780470443,
    "keep going": -489.2128911310366,
    "accelerate": -452.2018365540032
  },
  "('Z3', 'Z4', 'low', 'warmup', 'Z1', 'Z1', 'flat')": {
    "slow down": -501.7442985008423,
    "keep going": -507.6255413839805,
    "accelerate": -462.47754762858943
  },
  "('Z3', 'Z3', 'low', 'warmup', 'Z1', 'Z1', 'flat')": {
    "slow down": -496.9812093244059,
    "keep going": -513.045077525689,
    "accelerate": -468.03080847151335
  },
  "('Z3', 'Z3', 'low', 'warmup', 'Z1', 'Z1', 'downhill')": {
    "slow down": -432.588242499518,
    "keep going": -496.51210911310886,
    "accelerate": -496.32840285681425
  },
  "('Z3', 'Z2', 'low', 'warmup', 'Z1', 'Z1', 'flat')": {
    "slow down": -488.64512250949275,
    "keep going": -452.4643886469537,
    "accelerate": -491.6557023981947
  },
  "('Z2', 'Z1', 'low', 'warmup', 'Z1', 'Z1', 'downhill')": {
    "slow down": -490.57473340598284,
    "keep going": -437.37456548763396,
    "accelerate": -494.05340044526594
  },
  "('Z1', 'Z1', 'low', 'warmup', 'Z1', 'Z1', 'downhill')": {
    "slow down": 69.31615931818901,
    "keep going": -28.68414036190969,
    "accelerate": -151.86653804385833
  },
  "('Z1', 'Z2', 'low', 'warmup', 'Z1', 'Z1', 'uphill')": {
    "slow down": -131.51531690818405,
    "keep going": -403.961199980646,
    "accelerate": -418.6834557479163
  },
  "('Z2', 'Z4', 'low', 'warmup', 'Z1', 'Z1', 'flat')": {
    "slow down": -432.18681866247164,
    "keep going": -488.2616711501139,
    "accelerate": -489.5521027852923
  },
  "('Z3', 'Z4', 'low', 'warmup', 'Z1', 'Z1', 'downhill')": {
    "slow down": -472.6785088258317,
    "keep going": -500.525671595729,
    "accelerate": -495.8856928058795
  },
  "('Z4', 'Z5', 'low', 'warmup', 'Z1', 'Z1', 'downhill')": {
    "slow down": -452.8293083858705,
    "keep going": -498.8468026816199,
    "accelerate": -498.4675047423985
  },
  "('Z4', 'Z4', 'low', 'warmup', 'Z1', 'Z1', 'flat')": {
    "slow down": -463.7503008621604,
    "keep going": -502.8134332540808,
    "accelerate": -508.78516813196984
  },
  "('Z4', 'Z3', 'low', 'warmup', 'Z1', 'Z1', 'flat')": {
    "slow down": -467.3343747725684,
    "keep going": -495.75991897926014,
    "accelerate": -498.613169099784
  },
  "('Z4', 'Z5', 'low', 'warmup', 'Z1', 'Z1', 'flat')": {
    "slow down": -463.99830944750664,
    "keep going": -512.2000392633186,
    "accelerate": -504.237722814042
  },
  "('Z4', 'Z4', 'low', 'warmup', 'Z1', 'Z1', 'downhill')": {
    "slow down": -492.2537224491141,
    "keep going": -455.5380099849298,
    "accelerate": -491.7809723404924
  },
  "('Z4', 'Z2', 'low', 'warmup', 'Z1', 'Z1', 'downhill')": {
    "slow down": -400.63033384568104,
    "keep going": -402.86078126690495,
    "accelerate": -402.6841171841212
  },
  "('Z3', 'Z1', 'low', 'warmup', 'Z1', 'Z1', 'flat')": {
    "slow down": -500.67844270903595,
    "keep going": -500.707319739339,
    "accelerate": -418.9225820000553
  },
  "('Z2', 'Z4', 'low', 'warmup', 'Z1', 'Z1', 'downhill')": {
    "slow down": -453.1167641182804,
    "keep going": -462.8916474252643,
    "accelerate": -462.85222211984245
  },
  "('Z3', 'Z4', 'low', 'warmup', 'Z1', 'Z1', 'uphill')": {
    "slow down": -476.6992487154189,
    "keep going": -492.39741153592695,
    "accelerate": -492.2319267087663
  },
  "('Z3', 'Z3', 'low', 'warmup', 'Z1', 'Z1', 'uphill')": {
    "slow down": -456.2106826592423,
    "keep going": -492.14945064499267,
    "accelerate": -491.7433152683757
  },
  "('Z4', 'Z5', 'low', 'warmup', 'Z1', 'Z1', 'uphill')": {
    "slow down": -454.92016559814476,
    "keep going": -492.08545223956094,
    "accelerate": -492.62953813566855
  },
  "('Z4', 'Z4', 'low', 'warmup', 'Z1', 'Z1', 'uphill')": {
    "slow down": -451.52061952235675,
    "keep going": -490.68417895942525,
    "accelerate": -490.51423403427134
  },
  "('Z4', 'Z2', 'low', 'warmup', 'Z1', 'Z1', 'flat')": {
    "slow down": -480.90765970998575,
    "keep going": -481.0585659930228,
    "accelerate": -481.78704639821166
  },
  "('Z3', 'Z1', 'low', 'warmup', 'Z1', 'Z1', 'uphill')": {
    "slow down": -447.7729750658691,
    "keep going": -443.7837258948865,
    "accelerate": -450.0439421531417
  },
  "('Z3', 'Z5', 'low', 'warmup', 'Z1', 'Z1', 'flat')": {
    "slow down": -521.5774953117809,
    "keep going": -460.66579191730784,
    "accelerate": -497.63408745182926
  },
  "('Z3', 'Z2', 'low', 'warmup', 'Z1', 'Z1', 'downhill')": {
    "slow down": -421.5267993087119,
    "keep going": -487.60407494685904,
    "accelerate": -487.41581543947717
  },
  "('Z3', 'Z1', 'low', 'warmup', 'Z1', 'Z1', 'downhill')": {
    "slow down": -472.136958571957,
    "keep going": -471.6605617790905,
    "accelerate": -472.891333940932
  },
  "('Z3', 'Z5', 'low', 'warmup', 'Z1', 'Z1', 'downhill')": {
    "slow down": -483.27763770731275,
    "keep going": -482.476825739282,
    "accelerate": -459.6057354041009
  },
  "('Z3', 'Z2', 'low', 'warmup', 'Z1', 'Z1', 'uphill')": {
    "slow down": -484.2018529660375,
    "keep going": -442.2039697208545,
    "accelerate": -486.13780742305244
  },
  "('Z5', 'Z5', 'low', 'warmup', 'Z1', 'Z1', 'downhill')": {
    "slow down": -479.24609197517543,
    "keep going": -479.7429140320106,
    "accelerate": -478.8998338622819
  },
  "('Z4', 'Z3', 'low', 'warmup', 'Z1', 'Z1', 'uphill')": {
    "slow down": -432.80127025547284,
    "keep going": -475.1166704479236,
    "accelerate": -474.10304235460603
  },
  "('Z5', 'Z5', 'low', 'warmup', 'Z1', 'Z1', 'flat')": {
    "slow down": -494.86746568824583,
    "keep going": -509.5611217852168,
    "accelerate": -509.3989052750536
  },
  "('Z5', 'Z4', 'low', 'warmup', 'Z1', 'Z1', 'flat')": {
    "slow down": -480.16455290172433,
    "keep going": -482.75152992494264,
    "accelerate": -482.88438540292054
  },
  "('Z3', 'Z5', 'low', 'warmup', 'Z1', 'Z1', 'uphill')": {
    "slow down": -461.44583780082206,
    "keep going": -460.0853364974738,
    "accelerate": -457.60944297788086
  },
  "('Z4', 'Z3', 'low', 'warmup', 'Z1', 'Z1', 'downhill')": {
    "slow down": -442.6572269891489,
    "keep going": -472.86502447646063,
    "accelerate": -471.212497513383
  },
  "('Z2', 'Z4', 'low', 'warmup', 'Z1', 'Z1', 'uphill')": {
    "slow down": -433.80715955323245,
    "keep going": -431.36847346274567,
    "accelerate": -432.2798140324866
  },
  "('Z4', 'Z5', 'low', 'push', 'Z2', 'Z2', 'flat')": {
    "slow down": -718.4567610047615,
    "keep going": -719.4047695969509,
    "accelerate": -719.3259276247344
  },
  "('Z4', 'Z4', 'low', 'push', 'Z2', 'Z2', 'flat')": {
    "slow down": -717.8856736883178,
    "keep going": -718.7400050571018,
    "accelerate": -718.2341123693591
  },
  "('Z4', 'Z3', 'low', 'push', 'Z2', 'Z2', 'flat')": {
    "slow down": -717.3976546873245,
    "keep going": -717.4708252407263,
    "accelerate": -717.4760166925811
  },
  "('Z4', 'Z2', 'low', 'push', 'Z2', 'Z2', 'flat')": {
    "slow down": -709.0259325543122,
    "keep going": -709.2861217746046,
    "accelerate": -708.7753475056704
  },
  "('Z3', 'Z1', 'low', 'push', 'Z2', 'Z2', 'flat')": {
    "slow down": -720.4952560363724,
    "keep going": -720.4398438934392,
    "accelerate": -720.6079074631997
  },
  "('Z2', 'Z1', 'low', 'push', 'Z2', 'Z2', 'flat')": {
    "slow down": -721.4081202155811,
    "keep going": -721.0375429761333,
    "accelerate": -720.0679237649721
  },
  "('Z2', 'Z2', 'low', 'push', 'Z2', 'Z2', 'downhill')": {
    "slow down": -721.3570732667522,
    "keep going": -721.2573780665559,
    "accelerate": -721.259645469559
  },
  "('Z2', 'Z3', 'low', 'push', 'Z2', 'Z2', 'flat')": {
    "slow down": -716.5106319969581,
    "keep going": -721.198317029959,
    "accelerate": -721.8405729810289
  },
  "('Z2', 'Z2', 'low', 'push', 'Z2', 'Z2', 'flat')": {
    "slow down": -721.6259815004792,
    "keep going": -721.6232876659291,
    "accelerate": -721.5085790304294
  },
  "('Z2', 'Z2', 'low', 'push', 'Z2', 'Z2', 'uphill')": {
    "slow down": -721.3629462507967,
    "keep going": -721.2183724893765,
    "accelerate": -721.211985950638
  },
  "('Z2', 'Z1', 'low', 'push', 'Z2', 'Z2', 'downhill')": {
    "slow down": -720.9733124356939,
    "keep going": -720.9796713464979,
    "accelerate": -718.3006381131936
  },
  "('Z3', 'Z4', 'low', 'push', 'Z2', 'Z2', 'flat')": {
    "slow down": -720.5275281169698,
    "keep going": -721.8072153278151,
    "accelerate": -721.5589300903574
  },
  "('Z3', 'Z3', 'low', 'push', 'Z2', 'Z2', 'flat')": {
    "slow down": -720.0996875494245,
    "keep going": -721.2600800542876,
    "accelerate": -722.7136380462241
  },
  "('Z3', 'Z2', 'low', 'push', 'Z2', 'Z2', 'flat')": {
    "slow down": -720.8426617148224,
    "keep going": -721.7145830322813,
    "accelerate": -721.5740507603786
  },
  "('Z1', 'Z1', 'low', 'push', 'Z2', 'Z2', 'flat')": {
    "slow down": -721.1533647670643,
    "keep going": -721.1292535171575,
    "accelerate": -720.0860593909198
  },
  "('Z2', 'Z3', 'low', 'push', 'Z2', 'Z2', 'uphill')": {
    "slow down": -720.1531497095203,
    "keep going": -721.1793989737894,
    "accelerate": -721.5803333580021
  },
  "('Z3', 'Z4', 'low', 'push', 'Z2', 'Z2', 'uphill')": {
    "slow down": -716.9687268547156,
    "keep going": -717.2937415761961,
    "accelerate": -717.1563182759
  },
  "('Z4', 'Z5', 'low', 'push', 'Z2', 'Z2', 'downhill')": {
    "slow down": -707.8160422246322,
    "keep going": -708.0676422895765,
    "accelerate": -708.2166372584638
  },
  "('Z4', 'Z4', 'low', 'push', 'Z2', 'Z2', 'downhill')": {
    "slow down": -710.8215993531245,
    "keep going": -710.2912905007463,
    "accelerate": -710.8639210915554
  },
  "('Z4', 'Z3', 'low', 'push', 'Z2', 'Z2', 'downhill')": {
    "slow down": -700.280410897666,
    "keep going": -699.9045924552217,
    "accelerate": -700.649696355016
  },
  "('Z3', 'Z2', 'low', 'push', 'Z2', 'Z2', 'downhill')": {
    "slow down": -718.0308619024274,
    "keep going": -718.2114066408622,
    "accelerate": -718.176255779489
  },
  "('Z4', 'Z5', 'low', 'push', 'Z2', 'Z2', 'uphill')": {
    "slow down": -709.5249921709453,
    "keep going": -708.6770921800124,
    "accelerate": -710.4859205152161
  },
  "('Z5', 'Z5', 'low', 'push', 'Z2', 'Z2', 'flat')": {
    "slow down": -712.0818222181903,
    "keep going": -712.5764283896771,
    "accelerate": -712.4890039461307
  },
  "('Z2', 'Z4', 'low', 'push', 'Z2', 'Z2', 'flat')": {
    "slow down": -718.0437975393879,
    "keep going": -718.2897133718046,
    "accelerate": -718.4902273262334
  },
  "('Z1', 'Z1', 'low', 'push', 'Z2', 'Z2', 'uphill')": {
    "slow down": -720.7846177819399,
    "keep going": -719.9659850246991,
    "accelerate": -718.7012523745632
  },
  "('Z1', 'Z2', 'low', 'push', 'Z2', 'Z2', 'flat')": {
    "slow down": -719.2883350603869,
    "keep going": -714.5037907475466,
    "accelerate": -720.0884193653301
  },
  "('Z1', 'Z2', 'low', 'push', 'Z2', 'Z2', 'uphill')": {
    "slow down": -714.3587484226965,
    "keep going": -714.4675161553873,
    "accelerate": -714.618820550172
  },
  "('Z3', 'Z4', 'low', 'push', 'Z2', 'Z2', 'downhill')": {
    "slow down": -715.94734394574,
    "keep going": -716.4149725595828,
    "accelerate": -716.1770106254372
  },
  "('Z3', 'Z3', 'low', 'push', 'Z2', 'Z2', 'uphill')": {
    "slow down": -719.7917320216632,
    "keep going": -721.0401438306349,
    "accelerate": -721.6842059839651
  },
  "('Z3', 'Z3', 'low', 'push', 'Z2', 'Z2', 'downhill')": {
    "slow down": -719.6977070440215,
    "keep going": -720.9952674059184,
    "accelerate": -721.285532878231
  },
  "('Z3', 'Z2', 'low', 'push', 'Z2', 'Z2', 'uphill')": {
    "slow down": -719.2382075946281,
    "keep going": -719.1480651421805,
    "accelerate": -719.2748192961975
  },
  "('Z3', 'Z5', 'low', 'push', 'Z2', 'Z2', 'flat')": {
    "slow down": -720.7651797156194,
    "keep going": -720.8086939518283,
    "accelerate": -720.6306195049191
  },
  "('Z5', 'Z4', 'low', 'push', 'Z2', 'Z2', 'flat')": {
    "slow down": -704.6501968428685,
    "keep going": -704.1996599039658,
    "accelerate": -703.8581482726379
  },
  "('Z4', 'Z2', 'low', 'push', 'Z2', 'Z2', 'downhill')": {
    "slow down": -570.556288512432,
    "keep going": -575.732215401159,
    "accelerate": -576.7492626953676
  },
  "('Z2', 'Z1', 'low', 'push', 'Z2', 'Z2', 'uphill')": {
    "slow down": -721.1533458754234,
    "keep going": -721.0325513837356,
    "accelerate": -719.3466742485929
  },
  "('Z2', 'Z4', 'low', 'push', 'Z2', 'Z2', 'downhill')": {
    "slow down": -649.1153833728508,
    "keep going": -646.8571058181748,
    "accelerate": -649.9630434758209
  },
  "('Z1', 'Z2', 'low', 'push', 'Z2', 'Z2', 'downhill')": {
    "slow down": -710.7824886488066,
    "keep going": -710.6165282192878,
    "accelerate": -710.9295356569804
  },
  "('Z2', 'Z4', 'low', 'push', 'Z2', 'Z2', 'uphill')": {
    "slow down": -666.2786042185473,
    "keep going": -669.2565543507042,
    "accelerate": -668.8059486989553
  },
  "('Z5', 'Z5', 'low', 'push', 'Z2', 'Z2', 'uphill')": {
    "slow down": -700.6531124558378,
    "keep going": -699.8577355181255,
    "accelerate": -699.2143481349746
  },
  "('Z4', 'Z3', 'low', 'push', 'Z2', 'Z2', 'uphill')": {
    "slow down": -704.3404288510077,
    "keep going": -705.4883007819749,
    "accelerate": -705.159625950059
  },
  "('Z4', 'Z4', 'low', 'push', 'Z2', 'Z2', 'uphill')": {
    "slow down": -709.803384888613,
    "keep going": -709.8923211336103,
    "accelerate": -709.2970220172084
  },
  "('Z1', 'Z1', 'low', 'push', 'Z2', 'Z2', 'downhill')": {
    "slow down": -720.975929561074,
    "keep going": -720.9120907907051,
    "accelerate": -718.9649859015977
  },
  "('Z3', 'Z1', 'low', 'push', 'Z2', 'Z2', 'uphill')": {
    "slow down": -697.1570093752304,
    "keep going": -698.3402749923451,
    "accelerate": -698.5028691319886
  },
  "('Z2', 'Z3', 'low', 'push', 'Z2', 'Z2', 'downhill')": {
    "slow down": -719.5873377492429,
    "keep going": -721.1466531832932,
    "accelerate": -721.6590779300027
  },
  "('Z3', 'Z5', 'low', 'push', 'Z2', 'Z2', 'downhill')": {
    "slow down": -702.6869495825482,
    "keep going": -702.5643205894761,
    "accelerate": -703.3055963907101
  },
  "('Z3', 'Z5', 'low', 'push', 'Z2', 'Z2', 'uphill')": {
    "slow down": -696.8090128958122,
    "keep going": -696.7438687961455,
    "accelerate": -696.4716701985782
  },
  "('Z3', 'Z1', 'low', 'push', 'Z2', 'Z2', 'downhill')": {
    "slow down": -698.5994560009458,
    "keep going": -697.8906637714762,
    "accelerate": -699.6682945072562
  },
  "('Z5', 'Z4', 'low', 'push', 'Z2', 'Z2', 'downhill')": {
    "slow down": -577.4834110475355,
    "keep going": -580.7941032662476,
    "accelerate": -569.534333368278
  },
  "('Z4', 'Z2', 'low', 'push', 'Z2', 'Z2', 'uphill')": {
    "slow down": -560.9055918749934,
    "keep going": -553.8663351240903,
    "accelerate": -561.2325529531416
  },
  "('Z5', 'Z5', 'low', 'push', 'Z2', 'Z2', 'downhill')": {
    "slow down": -701.0208235303759,
    "keep going": -701.0908422377864,
    "accelerate": -701.7614682742546
  },
  "('Z4', 'Z5', 'low', 'push', 'Z3', 'Z3', 'flat')": {
    "slow down": -679.6273792847434,
    "keep going": -685.7988285198512,
    "accelerate": -685.9145293021829
  },
  "('Z4', 'Z4', 'low', 'push', 'Z3', 'Z3', 'flat')": {
    "slow down": -678.2492821723589,
    "keep going": -679.3752090326026,
    "accelerate": -685.0872414330482
  },
  "('Z4', 'Z3', 'low', 'push', 'Z3', 'Z3', 'flat')": {
    "slow down": -678.5893558485764,
    "keep going": -684.523549523091,
    "accelerate": -684.7588851085031
  },
  "('Z3', 'Z2', 'low', 'push', 'Z3', 'Z3', 'flat')": {
    "slow down": -681.1518235281667,
    "keep going": -680.945341252302,
    "accelerate": -675.4740102424066
  },
  "('Z3', 'Z1', 'low', 'push', 'Z3', 'Z3', 'flat')": {
    "slow down": -683.6975739079377,
    "keep going": -682.5556003365033,
    "accelerate": -683.6987214077175
  },
  "('Z2', 'Z1', 'low', 'push', 'Z3', 'Z3', 'flat')": {
    "slow down": -684.736265469203,
    "keep going": -684.9601616192534,
    "accelerate": -672.3931781895084
  },
  "('Z2', 'Z2', 'low', 'push', 'Z3', 'Z3', 'flat')": {
    "slow down": -680.0259948180712,
    "keep going": -621.9478731052897,
    "accelerate": -675.1655656699216
  },
  "('Z2', 'Z3', 'low', 'push', 'Z3', 'Z3', 'flat')": {
    "slow down": -669.7166396776076,
    "keep going": -683.4858455105067,
    "accelerate": -683.5223184817809
  },
  "('Z3', 'Z4', 'low', 'push', 'Z3', 'Z3', 'flat')": {
    "slow down": -674.5848479231455,
    "keep going": -684.3094649106365,
    "accelerate": -685.9716207934925
  },
  "('Z3', 'Z3', 'low', 'push', 'Z3', 'Z3', 'flat')": {
    "slow down": -676.828939621742,
    "keep going": -676.8085896299884,
    "accelerate": -680.6713161519502
  },
  "('Z1', 'Z1', 'low', 'push', 'Z3', 'Z3', 'flat')": {
    "slow down": -682.7575035407007,
    "keep going": -682.6444999234726,
    "accelerate": -680.0525870992986
  },
  "('Z1', 'Z2', 'low', 'push', 'Z3', 'Z3', 'flat')": {
    "slow down": -679.3908569854448,
    "keep going": -679.9480163068516,
    "accelerate": -680.1226664615521
  },
  "('Z2', 'Z4', 'low', 'push', 'Z3', 'Z3', 'flat')": {
    "slow down": -676.7283980857684,
    "keep going": -676.9583019706853,
    "accelerate": -676.8748529521005
  },
  "('Z5', 'Z5', 'low', 'push', 'Z3', 'Z3', 'flat')": {
    "slow down": -679.2743808290126,
    "keep going": -679.7141674610724,
    "accelerate": -679.5407213613568
  },
  "('Z4', 'Z2', 'low', 'push', 'Z3', 'Z3', 'flat')": {
    "slow down": -676.2119934859244,
    "keep going": -675.8819770243773,
    "accelerate": -675.9511030042303
  },
  "('Z5', 'Z4', 'low', 'push', 'Z3', 'Z3', 'flat')": {
    "slow down": -674.6816945968949,
    "keep going": -675.0245318859476,
    "accelerate": -674.9309676385922
  },
  "('Z3', 'Z5', 'low', 'push', 'Z3', 'Z3', 'flat')": {
    "slow down": -682.9071282812502,
    "keep going": -683.3848702927075,
    "accelerate": -683.4722802996573
  },
  "('Z3', 'Z2', 'low', 'cooldown', 'Z1', 'Z1', 'flat')": {
    "slow down": 0.0,
    "keep going": 0.0,
    "accelerate": 0.0
  },
  "('Z5', 'Z4', 'low', 'warmup', 'Z1', 'Z1', 'uphill')": {
    "slow down": -328.42195311682923,
    "keep going": -331.4906379762292,
    "accelerate": -337.9226127648134
  },
  "('Z5', 'Z4', 'low', 'push', 'Z2', 'Z2', 'uphill')": {
    "slow down": -548.5918537725697,
    "keep going": -545.9759241298174,
    "accelerate": -542.6664485010974
  },
  "('Z3', 'Z4', 'low', 'cooldown', 'Z1', 'Z1', 'flat')": {
    "slow down": 0.0,
    "keep going": 0.0,
    "accelerate": 0.0
  },
  "('Z5', 'Z4', 'low', 'warmup', 'Z1', 'Z1', 'downhill')": {
    "slow down": -394.6881237861523,
    "keep going": -390.9790856796639,
    "accelerate": -397.12945098607895
  },
  "('Z2', 'Z2', 'low', 'cooldown', 'Z1', 'Z1', 'flat')": {
    "slow down": 0.0,
    "keep going": 0.0,
    "accelerate": 0.0
  },
  "('Z4', 'Z2', 'low', 'warmup', 'Z1', 'Z1', 'uphill')": {
    "slow down": -394.50585706563254,
    "keep going": -385.8698125161055,
    "accelerate": -390.8675518278489
  },
  "('Z5', 'Z5', 'low', 'warmup', 'Z1', 'Z1', 'uphill')": {
    "slow down": -480.29110745632556,
    "keep going": -480.04499775099487,
    "accelerate": -482.5260856579488
  },
  "('Z4', 'Z4', 'low', 'cooldown', 'Z1', 'Z1', 'flat')": {
    "slow down": 0.0,
    "keep going": 0.0,
    "accelerate": 0.0
  },
  "('Z2', 'Z1', 'low', 'cooldown', 'Z1', 'Z1', 'flat')": {
    "slow down": 0.0,
    "keep going": 0.0,
    "accelerate": 0.0
  },
  "('Z3', 'Z1', 'low', 'cooldown', 'Z1', 'Z1', 'flat')": {
    "slow down": 0.0,
    "keep going": 0.0,
    "accelerate": 0.0
  },
  "('Z3', 'Z5', 'low', 'cooldown', 'Z1', 'Z1', 'flat')": {
    "slow down": 0.0,
    "keep going": 0.0,
    "accelerate": 0.0
  },
  "('Z1', 'Z1', 'low', 'cooldown', 'Z1', 'Z1', 'flat')": {
    "slow down": 0.0,
    "keep going": 0.0,
    "accelerate": 0.0
  },
  "('Z5', 'Z5', 'low', 'cooldown', 'Z1', 'Z1', 'flat')": {
    "slow down": 0.0,
    "keep going": 0.0,
    "accelerate": 0.0
  },
  "('Z4', 'Z5', 'low', 'cooldown', 'Z1', 'Z1', 'flat')": {
    "slow down": 0.0,
    "keep going": 0.0,
    "accelerate": 0.0
  },
  "('Z3', 'Z3', 'low', 'cooldown', 'Z1', 'Z1', 'flat')": {
    "slow down": 0.0,
    "keep going": 0.0,
    "accelerate": 0.0
  },
  "('Z2', 'Z3', 'low', 'cooldown', 'Z1', 'Z1', 'flat')": {
    "slow down": 0.0,
    "keep going": 0.0,
    "accelerate": 0.0
  },
  "('Z4', 'Z3', 'low', 'cooldown', 'Z1', 'Z1', 'flat')": {
    "slow down": 0.0,
    "keep going": 0.0,
    "accelerate": 0.0
  },
  "('Z2', 'Z4', 'low', 'cooldown', 'Z1', 'Z1', 'flat')": {
    "slow down": 0.0,
    "keep going": 0.0,
    "accelerate": 0.0
  }
}