{
  "('Z1', 'Z1', 'low', 'warmup', 'Z1', 'Z1', 'flat')": {
    "slow down": 49.72271432163815,
    "keep going": 49.63917484375187,
    "accelerate": 49.162716726837424
  },
  "('Z1', 'Z1', 'low', 'warmup', 'Z1', 'Z1', 'downhill')": {
    "slow down": 50.04953114529975,
    "keep going": 51.45095775370863,
    "accelerate": 49.200233166406065
  },
  "('Z1', 'Z1', 'low', 'warmup', 'Z1', 'Z1', 'uphill')": {
    "slow down": 50.05984476885845,
    "keep going": 51.421744754505035,
    "accelerate": 49.20812342977224
  },
  "('Z1', 'Z2', 'low', 'warmup', 'Z1', 'Z1', 'flat')": {
    "slow down": 50.10110281733692,
    "keep going": 47.857376934111045,
    "accelerate": 37.925341704564026
  },
  "('Z2', 'Z3', 'low', 'warmup', 'Z1', 'Z1', 'flat')": {
    "slow down": 43.39374494385209,
    "keep going": 6.360840430306996,
    "accelerate": -0.22692268562336482
  },
  "('Z2', 'Z2', 'low', 'warmup', 'Z1', 'Z1', 'flat')": {
    "slow down": 46.44636958844344,
    "keep going": 7.3383684585357845,
    "accelerate": 10.867120672054705
  },
  "('Z2', 'Z1', 'low', 'warmup', 'Z1', 'Z1', 'flat')": {
    "slow down": 50.06162288962599,
    "keep going": 33.34292407182576,
    "accelerate": 10.827136079283985
  },
  "('Z1', 'Z2', 'low', 'warmup', 'Z1', 'Z1', 'downhill')": {
    "slow down": 50.28157470947904,
    "keep going": 35.522538739900575,
    "accelerate": 21.455039755708334
  },
  "('Z2', 'Z3', 'low', 'warmup', 'Z1', 'Z1', 'uphill')": {
    "slow down": 23.19616784238652,
    "keep going": 0.0,
    "accelerate": 0.0
  },
  "('Z2', 'Z1', 'low', 'warmup', 'Z1', 'Z1', 'uphill')": {
    "slow down": 32.24508461720736,
    "keep going": 0.0,
    "accelerate": 4.114763929007705
  },
  "('Z1', 'Z2', 'low', 'warmup', 'Z1', 'Z1', 'uphill')": {
    "slow down": 49.98291710462023,
    "keep going": 36.16286151704591,
    "accelerate": 28.68974380710091
  },
  "('Z1', 'Z1', 'low', 'push', 'Z4', 'Z4', 'flat')": {
    "slow down": 20.016659333657852,
    "keep going": 17.359410362895563,
    "accelerate": 36.280962625070025
  },
  "('Z1', 'Z2', 'low', 'push', 'Z4', 'Z4', 'flat')": {
    "slow down": 14.470153026857487,
    "keep going": 18.21488375192032,
    "accelerate": 39.59815965427578
  },
  "('Z2', 'Z3', 'low', 'push', 'Z4', 'Z4', 'flat')": {
    "slow down": 32.13355848128923,
    "keep going": 36.70733834723188,
    "accelerate": 41.92415551337233
  },
  "('Z2', 'Z2', 'low', 'push', 'Z4', 'Z4', 'flat')": {
    "slow down": 8.145799948855121,
    "keep going": 11.216308316513311,
    "accelerate": 41.167058339715624
  },
  "('Z2', 'Z1', 'low', 'push', 'Z4', 'Z4', 'flat')": {
    "slow down": 5.786986165232102,
    "keep going": 2.6990504795947756,
    "accelerate": 34.22221563040039
  },
  "('Z1', 'Z1', 'low', 'push', 'Z4', 'Z4', 'downhill')": {
    "slow down": -0.18620117125966407,
    "keep going": -0.20669377086445292,
    "accelerate": 0.0
  },
  "('Z2', 'Z2', 'low', 'push', 'Z4', 'Z4', 'uphill')": {
    "slow down": 0.6959277068772901,
    "keep going": 1.9540966574568317,
    "accelerate": 19.90908264590567
  },
  "('Z2', 'Z4', 'low', 'push', 'Z4', 'Z4', 'flat')": {
    "slow down": 38.9796655190592,
    "keep going": 20.493785744019526,
    "accelerate": 21.660733558260247
  },
  "('Z3', 'Z3', 'low', 'push', 'Z4', 'Z4', 'flat')": {
    "slow down": 40.42113380446607,
    "keep going": 40.927097917674914,
    "accelerate": 45.27190176874022
  },
  "('Z3', 'Z3', 'low', 'push', 'Z4', 'Z4', 'uphill')": {
    "slow down": 34.00182039778744,
    "keep going": 41.79938321499917,
    "accelerate": 37.100056803416344
  },
  "('Z3', 'Z2', 'low', 'push', 'Z4', 'Z4', 'flat')": {
    "slow down": 33.167842349668256,
    "keep going": 40.99535499876173,
    "accelerate": 45.55099852089
  },
  "('Z3', 'Z4', 'low', 'push', 'Z4', 'Z4', 'flat')": {
    "slow down": 42.343991385160166,
    "keep going": 45.39178882631741,
    "accelerate": 43.33914525966131
  },
  "('Z3', 'Z3', 'low', 'push', 'Z4', 'Z4', 'downhill')": {
    "slow down": 37.6016868919727,
    "keep going": 34.7526524837549,
    "accelerate": 43.23274586421188
  },
  "('Z3', 'Z2', 'low', 'push', 'Z4', 'Z4', 'uphill')": {
    "slow down": 4.348717084163761,
    "keep going": 40.89317876900182,
    "accelerate": 15.839292056045707
  },
  "('Z3', 'Z4', 'low', 'push', 'Z4', 'Z4', 'uphill')": {
    "slow down": 42.539859098961074,
    "keep going": 34.916124330931915,
    "accelerate": 29.810887503885635
  },
  "('Z3', 'Z2', 'low', 'push', 'Z4', 'Z4', 'downhill')": {
    "slow down": 3.2480307945531504,
    "keep going": 41.477888093485525,
    "accelerate": 16.251309492382074
  },
  "('Z4', 'Z5', 'low', 'push', 'Z4', 'Z4', 'flat')": {
    "slow down": 47.85397148737292,
    "keep going": 44.888912579811304,
    "accelerate": 44.418119974021366
  },
  "('Z4', 'Z4', 'low', 'push', 'Z4', 'Z4', 'flat')": {
    "slow down": 45.95913029871239,
    "keep going": 47.68785192681628,
    "accelerate": 46.75505363723488
  },
  "('Z4', 'Z3', 'low', 'push', 'Z4', 'Z4', 'uphill')": {
    "slow down": 29.75185333622662,
    "keep going": 45.90221130265422,
    "accelerate": 28.126284349360702
  },
  "('Z2', 'Z2', 'low', 'push', 'Z4', 'Z4', 'downhill')": {
    "slow down": 1.2092204229039956,
    "keep going": 0.9783010767537347,
    "accelerate": 17.252054518988466
  },
  "('Z2', 'Z3', 'low', 'push', 'Z4', 'Z4', 'downhill')": {
    "slow down": 0.4351352725353845,
    "keep going": 11.131330533637176,
    "accelerate": 0.0
  },
  "('Z3', 'Z3', 'low', 'recover', 'Z2', 'Z2', 'flat')": {
    "slow down": 45.2736197941223,
    "keep going": 41.10629153803619,
    "accelerate": 41.144611534169904
  },
  "('Z3', 'Z2', 'low', 'recover', 'Z2', 'Z2', 'flat')": {
    "slow down": 43.87403936293389,
    "keep going": 38.31414487151325,
    "accelerate": 32.41637655971234
  },
  "('Z2', 'Z1', 'low', 'recover', 'Z2', 'Z2', 'flat')": {
    "slow down": 44.583436538732386,
    "keep going": 44.66726587873608,
    "accelerate": 47.25185886672473
  },
  "('Z2', 'Z2', 'low', 'recover', 'Z2', 'Z2', 'flat')": {
    "slow down": 45.374623924814316,
    "keep going": 45.568168863287504,
    "accelerate": 45.51438441722786
  },
  "('Z2', 'Z3', 'low', 'recover', 'Z2', 'Z2', 'flat')": {
    "slow down": 47.499491260199264,
    "keep going": 44.94595800392122,
    "accelerate": 40.98521611225218
  },
  "('Z1', 'Z1', 'low', 'recover', 'Z2', 'Z2', 'flat')": {
    "slow down": 42.78732235455031,
    "keep going": 43.10837852584486,
    "accelerate": 45.292743906669905
  },
  "('Z1', 'Z1', 'low', 'recover', 'Z2', 'Z2', 'uphill')": {
    "slow down": 42.79147514791546,
    "keep going": 23.814033287478736,
    "accelerate": 27.87369400671455
  },
  "('Z1', 'Z1', 'low', 'recover', 'Z2', 'Z2', 'downhill')": {
    "slow down": 42.978509195565195,
    "keep going": 29.794816851271715,
    "accelerate": 25.914691643903673
  },
  "('Z1', 'Z2', 'low', 'recover', 'Z2', 'Z2', 'flat')": {
    "slow down": 31.53940686757519,
    "keep going": 44.58794735417441,
    "accelerate": 24.741887474153774
  },
  "('Z1', 'Z2', 'low', 'recover', 'Z2', 'Z2', 'uphill')": {
    "slow down": 40.01501352737579,
    "keep going": 13.540241169293077,
    "accelerate": 0.1405833222270997
  },
  "('Z1', 'Z2', 'low', 'recover', 'Z2', 'Z2', 'downhill')": {
    "slow down": 38.13886190804928,
    "keep going": 13.672298585902533,
    "accelerate": 2.612675336277069
  },
  "('Z2', 'Z1', 'low', 'recover', 'Z2', 'Z2', 'downhill')": {
    "slow down": 45.77957610253678,
    "keep going": 38.24531187771964,
    "accelerate": 31.912241991892635
  },
  "('Z2', 'Z2', 'low', 'recover', 'Z2', 'Z2', 'uphill')": {
    "slow down": 45.377123851143196,
    "keep going": 47.77614147955374,
    "accelerate": 45.602018971063316
  },
  "('Z2', 'Z4', 'low', 'recover', 'Z2', 'Z2', 'flat')": {
    "slow down": 43.970825899449764,
    "keep going": 4.369431061406722,
    "accelerate": 0.0
  },
  "('Z2', 'Z2', 'low', 'recover', 'Z2', 'Z2', 'downhill')": {
    "slow down": 45.81199180571255,
    "keep going": 47.794707148931636,
    "accelerate": 45.64755199169412
  },
  "('Z1', 'Z1', 'low', 'push', 'Z5', 'Z5', 'flat')": {
    "slow down": -2.101426767792078,
    "keep going": -2.0195512548228542,
    "accelerate": -2.036905286818532
  },
  "('Z1', 'Z1', 'low', 'push', 'Z5', 'Z5', 'uphill')": {
    "slow down": -0.876840418664517,
    "keep going": -1.1234424849276214,
    "accelerate": -0.8477044516676028
  },
  "('Z1', 'Z1', 'low', 'push', 'Z5', 'Z5', 'downhill')": {
    "slow down": -1.0687342495934302,
    "keep going": -1.123958075190678,
    "accelerate": -1.087983858918706
  },
  "('Z1', 'Z2', 'low', 'push', 'Z5', 'Z5', 'downhill')": {
    "slow down": -0.3115656196678871,
    "keep going": -0.2896219018215288,
    "accelerate": -0.31309176182039133
  },
  "('Z1', 'Z2', 'low', 'push', 'Z5', 'Z5', 'flat')": {
    "slow down": -1.0833274022561268,
    "keep going": -0.9790854927693919,
    "accelerate": -1.0146601967680782
  },
  "('Z2', 'Z3', 'low', 'push', 'Z5', 'Z5', 'downhill')": {
    "slow down": -0.43839684616106667,
    "keep going": 0.3425241622687111,
    "accelerate": 27.300303485813064
  },
  "('Z2', 'Z2', 'low', 'push', 'Z5', 'Z5', 'flat')": {
    "slow down": -2.3414115705301373,
    "keep going": 4.382897728052553,
    "accelerate": 28.666708002586947
  },
  "('Z2', 'Z1', 'low', 'push', 'Z5', 'Z5', 'flat')": {
    "slow down": -1.503402628880842,
    "keep going": -1.4711739140106599,
    "accelerate": 5.120166482775736
  },
  "('Z2', 'Z3', 'low', 'push', 'Z5', 'Z5', 'flat')": {
    "slow down": -0.6955881368192651,
    "keep going": -0.36127676578947493,
    "accelerate": 19.43820494315144
  },
  "('Z3', 'Z4', 'low', 'push', 'Z5', 'Z5', 'flat')": {
    "slow down": 9.945669652544286,
    "keep going": 16.741378340951506,
    "accelerate": 35.63928787209495
  },
  "('Z3', 'Z3', 'low', 'push', 'Z5', 'Z5', 'flat')": {
    "slow down": 4.799540859094107,
    "keep going": 8.371297844873727,
    "accelerate": 29.58541714051092
  },
  "('Z3', 'Z2', 'low', 'push', 'Z5', 'Z5', 'flat')": {
    "slow down": -0.6956301476743945,
    "keep going": 3.0376860629546267,
    "accelerate": 9.880319571969425
  },
  "('Z2', 'Z4', 'low', 'push', 'Z5', 'Z5', 'flat')": {
    "slow down": -0.19204757570708578,
    "keep going": 0.3361644759604884,
    "accelerate": 26.02051472074372
  },
  "('Z3', 'Z5', 'low', 'push', 'Z5', 'Z5', 'uphill')": {
    "slow down": -0.04450762709008177,
    "keep going": 1.7740030960042152,
    "accelerate": 0.0
  },
  "('Z4', 'Z5', 'low', 'push', 'Z5', 'Z5', 'flat')": {
    "slow down": 20.410059023846717,
    "keep going": 23.420399029887783,
    "accelerate": 38.59392229754503
  },
  "('Z4', 'Z5', 'low', 'push', 'Z5', 'Z5', 'uphill')": {
    "slow down": 14.408197259596836,
    "keep going": 0.8833266043125617,
    "accelerate": 2.0529438173282033
  },
  "('Z4', 'Z4', 'low', 'push', 'Z5', 'Z5', 'flat')": {
    "slow down": 10.889093933833102,
    "keep going": 11.402779139943098,
    "accelerate": 35.193811407775854
  },
  "('Z4', 'Z3', 'low', 'push', 'Z5', 'Z5', 'downhill')": {
    "slow down": -0.16148779348768547,
    "keep going": 0.8240618735997642,
    "accelerate": 9.945851872003278
  },
  "('Z3', 'Z3', 'low', 'push', 'Z5', 'Z5', 'uphill')": {
    "slow down": 0.5884094577698986,
    "keep going": 2.729021822102405,
    "accelerate": 10.28701661161864
  },
  "('Z3', 'Z3', 'low', 'push', 'Z5', 'Z5', 'downhill')": {
    "slow down": 1.1344707587765708,
    "keep going": 13.54144441227599,
    "accelerate": 0.0
  },
  "('Z3', 'Z4', 'low', 'push', 'Z5', 'Z5', 'downhill')": {
    "slow down": 13.102650466899215,
    "keep going": 33.51692406012645,
    "accelerate": 18.201500386767663
  },
  "('Z5', 'Z5', 'low', 'push', 'Z5', 'Z5', 'flat')": {
    "slow down": 30.576247024551098,
    "keep going": 34.83380153827143,
    "accelerate": 34.55182778232612
  },
  "('Z4', 'Z3', 'low', 'push', 'Z5', 'Z5', 'flat')": {
    "slow down": 4.803250595327002,
    "keep going": 8.96885053453728,
    "accelerate": 15.505458546436158
  },
  "('Z4', 'Z2', 'low', 'push', 'Z5', 'Z5', 'flat')": {
    "slow down": -0.24635352190500434,
    "keep going": -0.1557457189221041,
    "accelerate": 7.09645982590572
  },
  "('Z3', 'Z1', 'low', 'push', 'Z5', 'Z5', 'flat')": {
    "slow down": -0.6938449184840458,
    "keep going": -0.52314371145352,
    "accelerate": 3.263026734873141
  },
  "('Z2', 'Z1', 'low', 'push', 'Z5', 'Z5', 'uphill')": {
    "slow down": -0.5103125851818172,
    "keep going": -0.6395042264071075,
    "accelerate": 0.8948658575087325
  },
  "('Z3', 'Z5', 'low', 'push', 'Z5', 'Z5', 'flat')": {
    "slow down": 20.38227434172477,
    "keep going": 37.39024724735906,
    "accelerate": 21.079874815765322
  },
  "('Z4', 'Z4', 'low', 'push', 'Z5', 'Z5', 'uphill')": {
    "slow down": 3.8195275384037903,
    "keep going": 16.472092306262777,
    "accelerate": 3.631984290768612
  },
  "('Z4', 'Z4', 'low', 'push', 'Z5', 'Z5', 'downhill')": {
    "slow down": 4.708652978114893,
    "keep going": 20.020692466968157,
    "accelerate": 1.2658739736598075
  },
  "('Z4', 'Z4', 'low', 'recover', 'Z1', 'Z1', 'flat')": {
    "slow down": 3.9225780771895247,
    "keep going": -1.3141202393076374,
    "accelerate": -1.099259614551023
  },
  "('Z4', 'Z3', 'low', 'recover', 'Z1', 'Z1', 'flat')": {
    "slow down": 20.136911525912875,
    "keep going": -0.12249941970719268,
    "accelerate": -1.1146693254129985
  },
  "('Z3', 'Z2', 'low', 'recover', 'Z1', 'Z1', 'flat')": {
    "slow down": 30.893618267435176,
    "keep going": 2.801011308471206,
    "accelerate": -0.14744871070727075
  },
  "('Z3', 'Z1', 'low', 'recover', 'Z1', 'Z1', 'downhill')": {
    "slow down": 0.09813355202273695,
    "keep going": 37.123617992278845,
    "accelerate": 0.07671759833459214
  },
  "('Z2', 'Z1', 'low', 'recover', 'Z1', 'Z1', 'flat')": {
    "slow down": 49.320185437144175,
    "keep going": 40.440341595582176,
    "accelerate": 30.821343864614533
  },
  "('Z2', 'Z1', 'low', 'recover', 'Z1', 'Z1', 'uphill')": {
    "slow down": 45.07960961600703,
    "keep going": 0.0,
    "accelerate": 2.6418340705997863
  },
  "('Z2', 'Z1', 'low', 'recover', 'Z1', 'Z1', 'downhill')": {
    "slow down": 47.452406060294834,
    "keep going": 0.0,
    "accelerate": 7.746783788782051
  },
  "('Z1', 'Z1', 'low', 'recover', 'Z1', 'Z1', 'flat')": {
    "slow down": 47.98427111662615,
    "keep going": 47.93524008591246,
    "accelerate": 47.47796520738299
  },
  "('Z1', 'Z2', 'low', 'recover', 'Z1', 'Z1', 'flat')": {
    "slow down": 49.501817979412266,
    "keep going": 47.772915095807875,
    "accelerate": 31.13440789913995
  },
  "('Z1', 'Z1', 'low', 'recover', 'Z1', 'Z1', 'uphill')": {
    "slow down": 47.942299926132904,
    "keep going": 48.016993401604694,
    "accelerate": 47.45806030645092
  },
  "('Z1', 'Z1', 'low', 'recover', 'Z1', 'Z1', 'downhill')": {
    "slow down": 48.00777099728026,
    "keep going": 47.92890434904216,
    "accelerate": 47.49950773954368
  },
  "('Z1', 'Z2', 'low', 'recover', 'Z1', 'Z1', 'uphill')": {
    "slow down": 49.493280639603626,
    "keep going": 27.434575882527774,
    "accelerate": 10.824401330252538
  },
  "('Z2', 'Z3', 'low', 'recover', 'Z1', 'Z1', 'flat')": {
    "slow down": 42.98206950021473,
    "keep going": 5.410723172155576,
    "accelerate": -0.1688259073048718
  },
  "('Z2', 'Z2', 'low', 'recover', 'Z1', 'Z1', 'flat')": {
    "slow down": 47.50159379366763,
    "keep going": 13.998559075888558,
    "accelerate": 4.702920851047875
  },
  "('Z2', 'Z3', 'low', 'recover', 'Z1', 'Z1', 'downhill')": {
    "slow down": 24.48405576630187,
    "keep going": 3.649063317592787,
    "accelerate": -0.16132764247789932
  },
  "('Z1', 'Z1', 'low', 'cooldown', 'Z1', 'Z1', 'flat')": {
    "slow down": 47.99378981565406,
    "keep going": 47.97505086946426,
    "accelerate": 47.50202345035673
  },
  "('Z1', 'Z1', 'low', 'cooldown', 'Z1', 'Z1', 'uphill')": {
    "slow down": 47.93844986020568,
    "keep going": 48.00262190033857,
    "accelerate": 47.48747017624589
  },
  "('Z1', 'Z1', 'low', 'cooldown', 'Z1', 'Z1', 'downhill')": {
    "slow down": 48.02066043092358,
    "keep going": 47.954341456072456,
    "accelerate": 47.50359283900421
  },
  "('Z1', 'Z2', 'low', 'cooldown', 'Z1', 'Z1', 'uphill')": {
    "slow down": 49.52296656466406,
    "keep going": 38.79443271496541,
    "accelerate": 31.626569039101007
  },
  "('Z2', 'Z3', 'low', 'cooldown', 'Z1', 'Z1', 'flat')": {
    "slow down": 44.23815013808525,
    "keep going": 17.536722966845343,
    "accelerate": 1.3519012156081969
  },
  "('Z2', 'Z2', 'low', 'cooldown', 'Z1', 'Z1', 'flat')": {
    "slow down": 47.461395361430995,
    "keep going": 15.52114428044434,
    "accelerate": 15.111163799186262
  },
  "('Z2', 'Z1', 'low', 'cooldown', 'Z1', 'Z1', 'flat')": {
    "slow down": 49.37812185419522,
    "keep going": 20.254214608276342,
    "accelerate": 22.1973907813456
  },
  "('Z1', 'Z2', 'low', 'cooldown', 'Z1', 'Z1', 'flat')": {
    "slow down": 49.54526931593879,
    "keep going": 47.86445888251138,
    "accelerate": 39.45753123816539
  },
  "('Z1', 'Z2', 'low', 'cooldown', 'Z1', 'Z1', 'downhill')": {
    "slow down": 49.50945392092007,
    "keep going": 40.83780824293826,
    "accelerate": 21.576925993206594
  },
  "('Z2', 'Z3', 'low', 'warmup', 'Z1', 'Z1', 'downhill')": {
    "slow down": 32.172783210857816,
    "keep going": 9.067898765894938,
    "accelerate": 0.0
  },
  "('Z2', 'Z1', 'low', 'warmup', 'Z1', 'Z1', 'downhill')": {
    "slow down": 39.90098896711769,
    "keep going": 0.0,
    "accelerate": 0.0
  },
  "('Z3', 'Z1', 'low', 'push', 'Z4', 'Z4', 'flat')": {
    "slow down": 9.257811515654797,
    "keep going": 18.43074167139029,
    "accelerate": 39.99790363544979
  },
  "('Z2', 'Z1', 'low', 'push', 'Z4', 'Z4', 'uphill')": {
    "slow down": -0.1344520324304676,
    "keep going": 1.3428937385773543,
    "accelerate": 12.065027319871882
  },
  "('Z2', 'Z3', 'low', 'push', 'Z4', 'Z4', 'uphill')": {
    "slow down": 0.07557250854682346,
    "keep going": 1.9711957595106957,
    "accelerate": 20.004590457059464
  },
  "('Z3', 'Z4', 'low', 'push', 'Z4', 'Z4', 'downhill')": {
    "slow down": 17.520529452822284,
    "keep going": 26.891215791096094,
    "accelerate": 46.47409270661807
  },
  "('Z3', 'Z5', 'low', 'push', 'Z4', 'Z4', 'flat')": {
    "slow down": 44.53884467490517,
    "keep going": 6.266370463557577,
    "accelerate": 0.38546079554512325
  },
  "('Z4', 'Z3', 'low', 'push', 'Z4', 'Z4', 'flat')": {
    "slow down": 40.550562357764825,
    "keep going": 43.6578700636385,
    "accelerate": 47.75921079199631
  },
  "('Z4', 'Z5', 'low', 'push', 'Z4', 'Z4', 'downhill')": {
    "slow down": 10.801544291876473,
    "keep going": 14.741622047235898,
    "accelerate": 46.7473101036844
  },
  "('Z4', 'Z3', 'low', 'push', 'Z4', 'Z4', 'downhill')": {
    "slow down": 42.782871456948946,
    "keep going": 27.205198241337083,
    "accelerate": 32.20600174989577
  },
  "('Z2', 'Z2', 'low', 'push', 'Z5', 'Z5', 'downhill')": {
    "slow down": -0.6210261536202974,
    "keep going": -0.6743528031884508,
    "accelerate": 9.747672325932067
  },
  "('Z4', 'Z3', 'low', 'push', 'Z5', 'Z5', 'uphill')": {
    "slow down": -0.25473869255281884,
    "keep going": 0.6543066056638445,
    "accelerate": 11.568052961148483
  },
  "('Z4', 'Z4', 'low', 'recover', 'Z1', 'Z1', 'downhill')": {
    "slow down": 1.3707352435917441,
    "keep going": -0.4991756976631929,
    "accelerate": -0.41520409269381137
  },
  "('Z3', 'Z1', 'low', 'recover', 'Z1', 'Z1', 'flat')": {
    "slow down": 38.98813163395357,
    "keep going": 13.738751620088163,
    "accelerate": 7.286601748052027
  },
  "('Z2', 'Z4', 'low', 'recover', 'Z1', 'Z1', 'downhill')": {
    "slow down": 0.05671324739825289,
    "keep going": 0.0,
    "accelerate": 0.0
  },
  "('Z2', 'Z4', 'low', 'recover', 'Z2', 'Z2', 'downhill')": {
    "slow down": 4.003635544316853,
    "keep going": 0.0,
    "accelerate": 0.0
  },
  "('Z5', 'Z5', 'low', 'push', 'Z5', 'Z5', 'uphill')": {
    "slow down": 37.22174187402067,
    "keep going": 15.11935722475325,
    "accelerate": 17.477944049196022
  },
  "('Z5', 'Z4', 'low', 'push', 'Z5', 'Z5', 'flat')": {
    "slow down": 11.885177690182157,
    "keep going": 24.37835636618532,
    "accelerate": 39.372656695214204
  },
  "('Z4', 'Z5', 'low', 'recover', 'Z1', 'Z1', 'flat')": {
    "slow down": -0.6216760021011407,
    "keep going": -0.5534828036299737,
    "accelerate": -0.6392325117740791
  },
  "('Z5', 'Z5', 'low', 'recover', 'Z1', 'Z1', 'downhill')": {
    "slow down": -0.408372481180736,
    "keep going": -0.6771874348700042,
    "accelerate": -0.7926456721946009
  },
  "('Z4', 'Z2', 'low', 'recover', 'Z1', 'Z1', 'flat')": {
    "slow down": 16.68817459581981,
    "keep going": 1.4650859570257357,
    "accelerate": 0.0
  },
  "('Z3', 'Z1', 'low', 'recover', 'Z1', 'Z1', 'uphill')": {
    "slow down": 12.935947588877724,
    "keep going": 0.0,
    "accelerate": 1.1749364839239058
  },
  "('Z1', 'Z2', 'low', 'recover', 'Z1', 'Z1', 'downhill')": {
    "slow down": 49.4982922902072,
    "keep going": 11.664637156924266,
    "accelerate": 9.726807850677469
  },
  "('Z2', 'Z4', 'low', 'recover', 'Z1', 'Z1', 'flat')": {
    "slow down": 5.497161418304263,
    "keep going": -0.16356367433807925,
    "accelerate": -0.29408434780507253
  },
  "('Z3', 'Z5', 'low', 'recover', 'Z1', 'Z1', 'uphill')": {
    "slow down": -0.1335151942069895,
    "keep going": 0.0,
    "accelerate": 0.0
  },
  "('Z3', 'Z4', 'low', 'recover', 'Z1', 'Z1', 'flat')": {
    "slow down": 0.734217341500663,
    "keep going": -0.15624810053907673,
    "accelerate": -0.28452114339396734
  },
  "('Z3', 'Z3', 'low', 'recover', 'Z1', 'Z1', 'flat')": {
    "slow down": 13.912457229603323,
    "keep going": 0.8653542925033999,
    "accelerate": -0.1850162302310536
  },
  "('Z2', 'Z2', 'low', 'cooldown', 'Z1', 'Z1', 'downhill')": {
    "slow down": 32.809706952703834,
    "keep going": 0.0,
    "accelerate": 0.0
  },
  "('Z2', 'Z4', 'low', 'cooldown', 'Z1', 'Z1', 'flat')": {
    "slow down": 14.738899941477431,
    "keep going": -0.15238721024441304,
    "accelerate": -0.5538888452700389
  },
  "('Z3', 'Z5', 'low', 'cooldown', 'Z1', 'Z1', 'uphill')": {
    "slow down": -0.12683526695592795,
    "keep going": 0.0,
    "accelerate": 0.0
  },
  "('Z3', 'Z4', 'low', 'cooldown', 'Z1', 'Z1', 'flat')": {
    "slow down": -0.06863271118912197,
    "keep going": -0.16208884052694947,
    "accelerate": -0.3195604695335294
  },
  "('Z3', 'Z3', 'low', 'cooldown', 'Z1', 'Z1', 'flat')": {
    "slow down": -0.036865042198352474,
    "keep going": -0.04395688348659073,
    "accelerate": -0.18794602701673815
  },
  "('Z3', 'Z2', 'low', 'cooldown', 'Z1', 'Z1', 'uphill')": {
    "slow down": 2.325404227461798,
    "keep going": 0.0,
    "accelerate": 0.0
  },
  "('Z3', 'Z5', 'low', 'cooldown', 'Z1', 'Z1', 'flat')": {
    "slow down": -0.13787809674647034,
    "keep going": 0.0,
    "accelerate": 0.0
  },
  "('Z4', 'Z5', 'low', 'cooldown', 'Z1', 'Z1', 'flat')": {
    "slow down": -0.14118080368975697,
    "keep going": 0.0,
    "accelerate": 0.0
  },
  "('Z4', 'Z4', 'low', 'cooldown', 'Z1', 'Z1', 'flat')": {
    "slow down": -0.12592628586789065,
    "keep going": 0.0,
    "accelerate": 0.0
  },
  "('Z4', 'Z3', 'low', 'cooldown', 'Z1', 'Z1', 'flat')": {
    "slow down": -0.008989737981797797,
    "keep going": 0.0,
    "accelerate": 0.0
  },
  "('Z3', 'Z2', 'low', 'cooldown', 'Z1', 'Z1', 'flat')": {
    "slow down": 2.9478716698637344,
    "keep going": -0.027221033056676797,
    "accelerate": 0.0
  },
  "('Z3', 'Z2', 'low', 'cooldown', 'Z1', 'Z1', 'downhill')": {
    "slow down": 0.023832968200381954,
    "keep going": 0.0,
    "accelerate": 0.0
  },
  "('Z3', 'Z1', 'low', 'cooldown', 'Z1', 'Z1', 'flat')": {
    "slow down": 0.09720513844402956,
    "keep going": 0.0,
    "accelerate": 0.0
  },
  "('Z2', 'Z1', 'low', 'cooldown', 'Z1', 'Z1', 'downhill')": {
    "slow down": 2.550989967172174,
    "keep going": 34.17320814719098,
    "accelerate": 0.0
  },
  "('Z2', 'Z2', 'low', 'warmup', 'Z1', 'Z1', 'uphill')": {
    "slow down": 43.174696948375434,
    "keep going": 4.277956186254776,
    "accelerate": 1.7412956945482716
  },
  "('Z4', 'Z5', 'low', 'push', 'Z4', 'Z4', 'uphill')": {
    "slow down": 47.78839642344465,
    "keep going": 17.465566667838672,
    "accelerate": 13.736505465454284
  },
  "('Z3', 'Z5', 'low', 'push', 'Z4', 'Z4', 'uphill')": {
    "slow down": 0.804083863993839,
    "keep going": 0.0,
    "accelerate": 0.0
  },
  "('Z1', 'Z2', 'low', 'push', 'Z5', 'Z5', 'uphill')": {
    "slow down": -0.2907144802196821,
    "keep going": -0.1835018024787627,
    "accelerate": 0.0
  },
  "('Z2', 'Z1', 'low', 'push', 'Z5', 'Z5', 'downhill')": {
    "slow down": -0.669485039854709,
    "keep going": -0.3606706474655204,
    "accelerate": 3.476738066432939
  },
  "('Z3', 'Z2', 'low', 'recover', 'Z1', 'Z1', 'downhill')": {
    "slow down": 9.708478402519289,
    "keep going": 0.0,
    "accelerate": 0.0
  },
  "('Z2', 'Z3', 'low', 'recover', 'Z1', 'Z1', 'uphill')": {
    "slow down": 12.961743364015195,
    "keep going": 0.0,
    "accelerate": -0.16113768539022888
  },
  "('Z3', 'Z4', 'low', 'recover', 'Z1', 'Z1', 'uphill')": {
    "slow down": -0.02624693520965751,
    "keep going": 0.0,
    "accelerate": 0.0
  },
  "('Z2', 'Z1', 'low', 'cooldown', 'Z1', 'Z1', 'uphill')": {
    "slow down": 41.04148959847086,
    "keep going": 0.0,
    "accelerate": 0.0
  },
  "('Z2', 'Z3', 'low', 'cooldown', 'Z1', 'Z1', 'downhill')": {
    "slow down": 20.86115668258013,
    "keep going": 4.160121817931594,
    "accelerate": -0.06590857762411893
  },
  "('Z2', 'Z3', 'low', 'cooldown', 'Z1', 'Z1', 'uphill')": {
    "slow down": 36.934139570173286,
    "keep going": 4.183186623407203,
    "accelerate": 0.3074612137687417
  },
  "('Z3', 'Z4', 'low', 'cooldown', 'Z1', 'Z1', 'downhill')": {
    "slow down": -0.021720735966305908,
    "keep going": 0.0,
    "accelerate": 0.0
  },
  "('Z2', 'Z2', 'low', 'cooldown', 'Z1', 'Z1', 'uphill')": {
    "slow down": 31.744437438609555,
    "keep going": 0.0,
    "accelerate": 0.0
  },
  "('Z2', 'Z4', 'low', 'warmup', 'Z1', 'Z1', 'flat')": {
    "slow down": -0.0021653152307179848,
    "keep going": -0.12120440675366687,
    "accelerate": 0.0
  },
  "('Z2', 'Z2', 'low', 'warmup', 'Z1', 'Z1', 'downhill')": {
    "slow down": 37.36831357411609,
    "keep going": 0.0,
    "accelerate": 2.1338360948607398
  },
  "('Z4', 'Z2', 'low', 'push', 'Z4', 'Z4', 'flat')": {
    "slow down": 4.8828856812901416,
    "keep going": 2.821654659398452,
    "accelerate": 42.769841962701584
  },
  "('Z2', 'Z1', 'low', 'recover', 'Z2', 'Z2', 'uphill')": {
    "slow down": 33.25065699786159,
    "keep going": 45.73216097831662,
    "accelerate": 39.56992095152459
  },
  "('Z2', 'Z3', 'low', 'recover', 'Z2', 'Z2', 'uphill')": {
    "slow down": 48.04422868389425,
    "keep going": 35.712123209661534,
    "accelerate": 31.002410723818556
  },
  "('Z3', 'Z5', 'low', 'push', 'Z5', 'Z5', 'downhill')": {
    "slow down": 13.338147395913875,
    "keep going": 0.0,
    "accelerate": 0.09986676226145524
  },
  "('Z4', 'Z5', 'low', 'push', 'Z5', 'Z5', 'downhill')": {
    "slow down": 38.68721366231114,
    "keep going": 19.216479480851202,
    "accelerate": 14.245841001201791
  },
  "('Z5', 'Z5', 'low', 'push', 'Z5', 'Z5', 'downhill')": {
    "slow down": 37.26873893792768,
    "keep going": 16.593169680695674,
    "accelerate": 11.213127519201532
  },
  "('Z5', 'Z5', 'low', 'recover', 'Z1', 'Z1', 'flat')": {
    "slow down": 2.3751022156186927,
    "keep going": -2.4134982027019083,
    "accelerate": -2.676070045007056
  },
  "('Z5', 'Z4', 'low', 'recover', 'Z1', 'Z1', 'flat')": {
    "slow down": 11.168361097481789,
    "keep going": -0.562622955388886,
    "accelerate": -0.8316174145061721
  },
  "('Z4', 'Z2', 'low', 'recover', 'Z1', 'Z1', 'uphill')": {
    "slow down": 0.9693012490091939,
    "keep going": 0.0,
    "accelerate": 0.0
  },
  "('Z2', 'Z2', 'low', 'recover', 'Z1', 'Z1', 'downhill')": {
    "slow down": 20.716194968475428,
    "keep going": 1.777922477543779,
    "accelerate": 3.507583692073675
  },
  "('Z4', 'Z2', 'low', 'push', 'Z5', 'Z5', 'uphill')": {
    "slow down": -0.2645511319290642,
    "keep going": 0.7254887135421264,
    "accelerate": 0.0
  },
  "('Z3', 'Z2', 'low', 'push', 'Z5', 'Z5', 'downhill')": {
    "slow down": -0.39047277554116494,
    "keep going": -0.14965304482246752,
    "accelerate": 7.033326025495604
  },
  "('Z4', 'Z3', 'low', 'recover', 'Z1', 'Z1', 'downhill')": {
    "slow down": 3.6703320442488674,
    "keep going": -0.1007744449690906,
    "accelerate": -0.2623110248706773
  },
  "('Z2', 'Z1', 'low', 'push', 'Z4', 'Z4', 'downhill')": {
    "slow down": 4.561754587720206,
    "keep going": 0.0,
    "accelerate": 0.0
  },
  "('Z2', 'Z4', 'low', 'push', 'Z4', 'Z4', 'uphill')": {
    "slow down": 0.9807099411272541,
    "keep going": 0.0,
    "accelerate": 0.0
  },
  "('Z4', 'Z4', 'low', 'push', 'Z4', 'Z4', 'uphill')": {
    "slow down": 45.33092747413021,
    "keep going": 47.9218886652509,
    "accelerate": 46.66177335895497
  },
  "('Z3', 'Z2', 'low', 'recover', 'Z1', 'Z1', 'uphill')": {
    "slow down": 6.975060416751331,
    "keep going": 0.0,
    "accelerate": 0.0
  },
  "('Z2', 'Z2', 'low', 'recover', 'Z1', 'Z1', 'uphill')": {
    "slow down": 34.06526497352642,
    "keep going": 0.0,
    "accelerate": 0.0
  },
  "('Z4', 'Z4', 'low', 'push', 'Z4', 'Z4', 'downhill')": {
    "slow down": 46.578354138047885,
    "keep going": 47.90644981230783,
    "accelerate": 46.7793318891521
  },
  "('Z3', 'Z4', 'low', 'recover', 'Z2', 'Z2', 'flat')": {
    "slow down": 45.701641188341284,
    "keep going": 27.2362182695209,
    "accelerate": 2.591057279238731
  },
  "('Z2', 'Z3', 'low', 'push', 'Z5', 'Z5', 'uphill')": {
    "slow down": 1.6674211492121627,
    "keep going": 7.617539964299638,
    "accelerate": 31.61108621631814
  },
  "('Z4', 'Z2', 'low', 'recover', 'Z1', 'Z1', 'downhill')": {
    "slow down": 29.96809227064522,
    "keep going": 0.352459271813822,
    "accelerate": 0.41198397671247866
  },
  "('Z4', 'Z4', 'low', 'recover', 'Z1', 'Z1', 'uphill')": {
    "slow down": -0.12610889077058082,
    "keep going": -0.1626932442106899,
    "accelerate": 0.0
  },
  "('Z2', 'Z3', 'low', 'recover', 'Z2', 'Z2', 'downhill')": {
    "slow down": 48.38638862171886,
    "keep going": 34.519911831768724,
    "accelerate": 19.23805024035014
  },
  "('Z2', 'Z4', 'low', 'push', 'Z5', 'Z5', 'downhill')": {
    "slow down": -0.18968490887560152,
    "keep going": 32.92353280068081,
    "accelerate": 2.162191884880663
  },
  "('Z3', 'Z1', 'low', 'recover', 'Z2', 'Z2', 'flat')": {
    "slow down": 44.74175442965044,
    "keep going": 32.57719233166592,
    "accelerate": 32.53291155807821
  },
  "('Z3', 'Z1', 'low', 'push', 'Z4', 'Z4', 'uphill')": {
    "slow down": 0.5502182369025526,
    "keep going": 0.0,
    "accelerate": 9.771531482419238
  },
  "('Z2', 'Z2', 'low', 'push', 'Z5', 'Z5', 'uphill')": {
    "slow down": -0.5981195446173789,
    "keep going": -0.40650321311771487,
    "accelerate": 14.849156842040964
  },
  "('Z3', 'Z2', 'low', 'push', 'Z5', 'Z5', 'uphill')": {
    "slow down": -0.5078310818792324,
    "keep going": -0.05317198426968104,
    "accelerate": 8.369936134227718
  },
  "('Z3', 'Z1', 'low', 'push', 'Z5', 'Z5', 'downhill')": {
    "slow down": -0.316673747690643,
    "keep going": 0.0843659736132874,
    "accelerate": 0.0
  },
  "('Z4', 'Z5', 'low', 'recover', 'Z1', 'Z1', 'downhill')": {
    "slow down": -0.24226639831957525,
    "keep going": 0.0,
    "accelerate": 0.0
  },
  "('Z4', 'Z3', 'low', 'recover', 'Z1', 'Z1', 'uphill')": {
    "slow down": -0.056184888490693564,
    "keep going": -0.14518937813159158,
    "accelerate": -0.2438420826094249
  },
  "('Z2', 'Z4', 'low', 'recover', 'Z1', 'Z1', 'uphill')": {
    "slow down": 0.0,
    "keep going": -0.14571498678563763,
    "accelerate": 0.0
  },
  "('Z3', 'Z5', 'low', 'recover', 'Z1', 'Z1', 'flat')": {
    "slow down": -0.13409465326422326,
    "keep going": 0.0,
    "accelerate": 0.0
  },
  "('Z3', 'Z3', 'low', 'recover', 'Z2', 'Z2', 'uphill')": {
    "slow down": 45.13951587904782,
    "keep going": 14.531893433897643,
    "accelerate": 0.0
  },
  "('Z5', 'Z4', 'low', 'push', 'Z5', 'Z5', 'downhill')": {
    "slow down": 14.323971125120067,
    "keep going": 0.0,
    "accelerate": 0.0
  },
  "('Z5', 'Z4', 'low', 'push', 'Z5', 'Z5', 'uphill')": {
    "slow down": 11.549220987886065,
    "keep going": 3.375108964789985,
    "accelerate": 3.8153746927841308
  },
  "('Z2', 'Z4', 'low', 'recover', 'Z2', 'Z2', 'uphill')": {
    "slow down": 13.30705973985157,
    "keep going": 0.0,
    "accelerate": 0.0
  },
  "('Z3', 'Z2', 'low', 'recover', 'Z2', 'Z2', 'downhill')": {
    "slow down": 32.47006087607874,
    "keep going": 0.0,
    "accelerate": 0.0
  },
  "('Z3', 'Z4', 'low', 'recover', 'Z2', 'Z2', 'uphill')": {
    "slow down": 31.167698893439773,
    "keep going": 0.0,
    "accelerate": 0.0
  },
  "('Z3', 'Z3', 'low', 'recover', 'Z2', 'Z2', 'downhill')": {
    "slow down": 45.564984596713444,
    "keep going": 4.350989690679778,
    "accelerate": 13.746994142377776
  },
  "('Z3', 'Z1', 'low', 'push', 'Z4', 'Z4', 'downhill')": {
    "slow down": 1.4608850580527457,
    "keep going": 0.0,
    "accelerate": 14.175080818757088
  },
  "('Z3', 'Z4', 'low', 'recover', 'Z2', 'Z2', 'downhill')": {
    "slow down": 28.22335973830294,
    "keep going": 0.0,
    "accelerate": 0.0
  },
  "('Z2', 'Z4', 'low', 'push', 'Z5', 'Z5', 'uphill')": {
    "slow down": -0.04093119695858949,
    "keep going": 0.0,
    "accelerate": 0.0
  },
  "('Z5', 'Z4', 'low', 'recover', 'Z1', 'Z1', 'downhill')": {
    "slow down": 1.186835333132685,
    "keep going": 0.0,
    "accelerate": 0.0
  },
  "('Z3', 'Z2', 'low', 'recover', 'Z2', 'Z2', 'uphill')": {
    "slow down": 4.3997115003760525,
    "keep going": 38.12700201912704,
    "accelerate": 0.0
  },
  "('Z4', 'Z2', 'low', 'push', 'Z4', 'Z4', 'downhill')": {
    "slow down": 1.043509477141736,
    "keep going": 13.887302453524047,
    "accelerate": 0.0
  },
  "('Z4', 'Z3', 'low', 'recover', 'Z2', 'Z2', 'flat')": {
    "slow down": 43.97331048232881,
    "keep going": 22.72403314170556,
    "accelerate": 25.380101985814292
  },
  "('Z3', 'Z5', 'low', 'recover', 'Z2', 'Z2', 'flat')": {
    "slow down": 20.388965893805693,
    "keep going": -0.1229022475373824,
    "accelerate": 0.0
  },
  "('Z3', 'Z3', 'low', 'recover', 'Z1', 'Z1', 'uphill')": {
    "slow down": 1.228361782489718,
    "keep going": 0.0,
    "accelerate": 0.0
  },
  "('Z4', 'Z4', 'low', 'recover', 'Z2', 'Z2', 'flat')": {
    "slow down": 41.56569811287747,
    "keep going": 13.511047629739384,
    "accelerate": 4.8533256912369005
  },
  "('Z3', 'Z1', 'low', 'recover', 'Z2', 'Z2', 'uphill')": {
    "slow down": 0.0,
    "keep going": 0.0,
    "accelerate": 3.1939583519208425
  },
  "('Z3', 'Z5', 'low', 'recover', 'Z2', 'Z2', 'uphill')": {
    "slow down": 0.720656085007825,
    "keep going": 0.0,
    "accelerate": 0.0
  },
  "('Z4', 'Z2', 'low', 'push', 'Z4', 'Z4', 'uphill')": {
    "slow down": 12.951995834931672,
    "keep going": 3.1288293639559583,
    "accelerate": 0.0
  },
  "('Z5', 'Z5', 'low', 'push', 'Z4', 'Z4', 'flat')": {
    "slow down": 41.299355357875186,
    "keep going": 16.073757295509864,
    "accelerate": 8.172126939326766
  },
  "('Z5', 'Z4', 'medium', 'push', 'Z5', 'Z5', 'flat')": {
    "slow down": 33.203123315480106,
    "keep going": 37.00024063331151,
    "accelerate": 45.82550165586483
  },
  "('Z5', 'Z5', 'medium', 'push', 'Z5', 'Z5', 'flat')": {
    "slow down": 41.78898564060606,
    "keep going": 42.62917643783459,
    "accelerate": 42.671980472738575
  },
  "('Z5', 'Z5', 'medium', 'push', 'Z5', 'Z5', 'downhill')": {
    "slow down": 43.86908194831367,
    "keep going": 44.23467010839443,
    "accelerate": 40.76322582040122
  },
  "('Z4', 'Z4', 'medium', 'push', 'Z5', 'Z5', 'flat')": {
    "slow down": 31.160334463137907,
    "keep going": 35.294999673063906,
    "accelerate": 38.07944911650291
  },
  "('Z4', 'Z4', 'medium', 'push', 'Z4', 'Z4', 'flat')": {
    "slow down": 44.52556438099618,
    "keep going": 45.82077003765701,
    "accelerate": 45.362194463394225
  },
  "('Z4', 'Z5', 'medium', 'push', 'Z5', 'Z5', 'flat')": {
    "slow down": 32.39223055495523,
    "keep going": 37.34233218827416,
    "accelerate": 39.48141543372611
  },
  "('Z4', 'Z5', 'medium', 'push', 'Z5', 'Z5', 'uphill')": {
    "slow down": 37.1694853895045,
    "keep going": 1.6908242059175866,
    "accelerate": 0.0
  },
  "('Z4', 'Z4', 'medium', 'push', 'Z5', 'Z5', 'uphill')": {
    "slow down": 33.24845036962454,
    "keep going": 3.303152364775105,
    "accelerate": 5.075301622838666
  },
  "('Z4', 'Z2', 'low', 'push', 'Z5', 'Z5', 'downhill')": {
    "slow down": -0.2739409938257082,
    "keep going": -0.06717332358186877,
    "accelerate": 1.018107040382216
  },
  "('Z4', 'Z4', 'medium', 'push', 'Z5', 'Z5', 'downhill')": {
    "slow down": 34.153454222835165,
    "keep going": 6.213488891632202,
    "accelerate": 7.336617746508553
  },
  "('Z4', 'Z4', 'medium', 'recover', 'Z1', 'Z1', 'flat')": {
    "slow down": 19.933004290292452,
    "keep going": 0.0,
    "accelerate": -0.356362921765455
  },
  "('Z5', 'Z4', 'medium', 'push', 'Z5', 'Z5', 'uphill')": {
    "slow down": 34.170128195189974,
    "keep going": 0.0,
    "accelerate": 0.0
  },
  "('Z4', 'Z5', 'medium', 'push', 'Z4', 'Z4', 'downhill')": {
    "slow down": 45.486024473238864,
    "keep going": 0.0,
    "accelerate": 0.0
  },
  "('Z4', 'Z5', 'medium', 'push', 'Z5', 'Z5', 'downhill')": {
    "slow down": 36.91882681040975,
    "keep going": 26.9895868344394,
    "accelerate": 28.72762888829002
  },
  "('Z4', 'Z3', 'medium', 'push', 'Z5', 'Z5', 'flat')": {
    "slow down": 10.896737061678444,
    "keep going": 17.746988406816335,
    "accelerate": 36.50838910986967
  },
  "('Z4', 'Z4', 'medium', 'push', 'Z4', 'Z4', 'uphill')": {
    "slow down": 45.241895052393986,
    "keep going": 46.710034177332616,
    "accelerate": 45.24977374976734
  },
  "('Z3', 'Z4', 'low', 'push', 'Z5', 'Z5', 'uphill')": {
    "slow down": 6.605953661755192,
    "keep going": 0.0,
    "accelerate": 0.0
  },
  "('Z4', 'Z3', 'medium', 'recover', 'Z1', 'Z1', 'flat')": {
    "slow down": 36.05540570878809,
    "keep going": 16.87681741119989,
    "accelerate": -0.24267733833911473
  },
  "('Z4', 'Z5', 'medium', 'push', 'Z4', 'Z4', 'flat')": {
    "slow down": 46.52919287156221,
    "keep going": 32.76882055254977,
    "accelerate": 30.96194593291697
  },
  "('Z4', 'Z3', 'medium', 'push', 'Z5', 'Z5', 'downhill')": {
    "slow down": 29.40004481680497,
    "keep going": 0.0,
    "accelerate": 6.433402237703875
  },
  "('Z3', 'Z3', 'medium', 'recover', 'Z1', 'Z1', 'flat')": {
    "slow down": 6.464754723452023,
    "keep going": 0.0,
    "accelerate": 0.0
  },
  "('Z4', 'Z4', 'medium', 'push', 'Z4', 'Z4', 'downhill')": {
    "slow down": 44.70241383859839,
    "keep going": 46.71475505916439,
    "accelerate": 44.16776081766645
  },
  "('Z4', 'Z5', 'medium', 'push', 'Z4', 'Z4', 'uphill')": {
    "slow down": 45.721526624121644,
    "keep going": 4.109010229608965,
    "accelerate": 0.0
  },
  "('Z4', 'Z4', 'medium', 'recover', 'Z2', 'Z2', 'flat')": {
    "slow down": 38.589104476462865,
    "keep going": 24.96260625864123,
    "accelerate": 18.30856037023937
  },
  "('Z4', 'Z3', 'medium', 'recover', 'Z2', 'Z2', 'flat')": {
    "slow down": 41.198978001318885,
    "keep going": 16.808278006019222,
    "accelerate": 3.4814147417520482
  },
  "('Z3', 'Z2', 'medium', 'recover', 'Z2', 'Z2', 'flat')": {
    "slow down": 40.384471642188956,
    "keep going": 7.522527367974167,
    "accelerate": 1.1777152438039558
  },
  "('Z5', 'Z5', 'low', 'push', 'Z4', 'Z4', 'uphill')": {
    "slow down": 44.06795228055909,
    "keep going": 3.9998261508556725,
    "accelerate": 4.337295098407585
  },
  "('Z4', 'Z3', 'medium', 'push', 'Z4', 'Z4', 'flat')": {
    "slow down": 27.37000440781568,
    "keep going": 39.41297448573953,
    "accelerate": 46.78829442944092
  },
  "('Z4', 'Z3', 'medium', 'push', 'Z5', 'Z5', 'uphill')": {
    "slow down": 9.16732325740526,
    "keep going": 0.0,
    "accelerate": 0.9423896696882985
  },
  "('Z3', 'Z3', 'medium', 'push', 'Z5', 'Z5', 'downhill')": {
    "slow down": 0.6864686697929263,
    "keep going": 0.0,
    "accelerate": 0.0
  },
  "('Z4', 'Z3', 'medium', 'push', 'Z4', 'Z4', 'uphill')": {
    "slow down": 33.35933518405025,
    "keep going": 0.0,
    "accelerate": 0.0
  },
  "('Z3', 'Z3', 'medium', 'push', 'Z5', 'Z5', 'flat')": {
    "slow down": 3.66058115168463,
    "keep going": 1.7269109291244766,
    "accelerate": 2.600705084258033
  },
  "('Z5', 'Z4', 'low', 'push', 'Z4', 'Z4', 'flat')": {
    "slow down": 11.003503693654196,
    "keep going": 0.0,
    "accelerate": 0.0
  },
  "('Z3', 'Z3', 'low', 'recover', 'Z1', 'Z1', 'downhill')": {
    "slow down": 2.6623018474922038,
    "keep going": 0.0,
    "accelerate": 0.0
  },
  "('Z5', 'Z5', 'low', 'push', 'Z4', 'Z4', 'downhill')": {
    "slow down": 29.776348554962055,
    "keep going": 0.0,
    "accelerate": 0.0
  },
  "('Z4', 'Z3', 'medium', 'push', 'Z4', 'Z4', 'downhill')": {
    "slow down": 31.630410836702676,
    "keep going": 3.4583464743025205,
    "accelerate": 3.6873423456085987
  },
  "('Z3', 'Z2', 'medium', 'push', 'Z5', 'Z5', 'flat')": {
    "slow down": -0.7107797372219952,
    "keep going": 4.394661309226581,
    "accelerate": 0.405086318272299
  },
  "('Z3', 'Z2', 'medium', 'recover', 'Z1', 'Z1', 'flat')": {
    "slow down": 37.84996128898998,
    "keep going": 0.0,
    "accelerate": 0.0
  },
  "('Z3', 'Z1', 'medium', 'recover', 'Z1', 'Z1', 'downhill')": {
    "slow down": 38.22925350279889,
    "keep going": 1.4903997820075428,
    "accelerate": 0.0
  },
  "('Z2', 'Z1', 'medium', 'recover', 'Z1', 'Z1', 'flat')": {
    "slow down": 48.22249953424979,
    "keep going": 33.66020234096455,
    "accelerate": 31.257115114464593
  },
  "('Z4', 'Z5', 'low', 'recover', 'Z2', 'Z2', 'flat')": {
    "slow down": 27.70644061840209,
    "keep going": 0.0,
    "accelerate": 0.0
  },
  "('Z3', 'Z1', 'medium', 'recover', 'Z1', 'Z1', 'flat')": {
    "slow down": 40.59449321846928,
    "keep going": 35.0871644840555,
    "accelerate": 25.594654005562173
  },
  "('Z2', 'Z1', 'medium', 'recover', 'Z1', 'Z1', 'downhill')": {
    "slow down": 46.812842619501815,
    "keep going": 20.96995313120759,
    "accelerate": 14.57301915992876
  },
  "('Z5', 'Z5', 'medium', 'push', 'Z5', 'Z5', 'uphill')": {
    "slow down": 44.33372559311001,
    "keep going": 43.57195443728171,
    "accelerate": 43.32410198568274
  },
  "('Z4', 'Z2', 'medium', 'recover', 'Z1', 'Z1', 'flat')": {
    "slow down": 38.48594715157526,
    "keep going": -0.03820812843195509,
    "accelerate": 0.0
  },
  "('Z5', 'Z5', 'medium', 'recover', 'Z1', 'Z1', 'flat')": {
    "slow down": 28.752712318303168,
    "keep going": 9.817719912288116,
    "accelerate": 16.381420834124583
  },
  "('Z5', 'Z4', 'medium', 'recover', 'Z1', 'Z1', 'flat')": {
    "slow down": 32.935141316333656,
    "keep going": 15.759742729258138,
    "accelerate": 7.714668861337264
  },
  "('Z4', 'Z2', 'medium', 'recover', 'Z1', 'Z1', 'downhill')": {
    "slow down": 38.956315393550106,
    "keep going": 15.052395501234068,
    "accelerate": 6.035448085545637
  },
  "('Z2', 'Z1', 'medium', 'recover', 'Z1', 'Z1', 'uphill')": {
    "slow down": 45.494156532244645,
    "keep going": 32.49095677803366,
    "accelerate": 4.836746186326543
  },
  "('Z4', 'Z2', 'medium', 'push', 'Z5', 'Z5', 'flat')": {
    "slow down": -0.14038491465418934,
    "keep going": 0.9189861883913947,
    "accelerate": 33.44196329798879
  },
  "('Z4', 'Z5', 'medium', 'recover', 'Z1', 'Z1', 'flat')": {
    "slow down": 0.5139829676299816,
    "keep going": -0.27181400821951884,
    "accelerate": -0.48518710038537344
  },
  "('Z5', 'Z4', 'medium', 'recover', 'Z1', 'Z1', 'downhill')": {
    "slow down": 13.214414608597462,
    "keep going": -0.26561600201436436,
    "accelerate": -0.4174663747426595
  },
  "('Z3', 'Z1', 'medium', 'recover', 'Z1', 'Z1', 'uphill')": {
    "slow down": 40.26462858338794,
    "keep going": 0.0,
    "accelerate": 0.47171600648805234
  },
  "('Z3', 'Z2', 'medium', 'push', 'Z5', 'Z5', 'downhill')": {
    "slow down": -0.3802882307525639,
    "keep going": -0.16865042252816487,
    "accelerate": 1.360422920313619
  },
  "('Z2', 'Z2', 'medium', 'push', 'Z5', 'Z5', 'flat')": {
    "slow down": -0.2877779119237693,
    "keep going": 5.5001138082960725,
    "accelerate": 0.0
  },
  "('Z1', 'Z1', 'medium', 'recover', 'Z1', 'Z1', 'flat')": {
    "slow down": 47.9743357407558,
    "keep going": 31.27747596876251,
    "accelerate": 27.872952788008472
  },
  "('Z3', 'Z2', 'medium', 'push', 'Z4', 'Z4', 'flat')": {
    "slow down": 25.17689610712641,
    "keep going": 11.207625720383454,
    "accelerate": 4.391979628515046
  },
  "('Z4', 'Z2', 'medium', 'recover', 'Z1', 'Z1', 'uphill')": {
    "slow down": 0.14843982792530594,
    "keep going": 0.0,
    "accelerate": 0.0
  },
  "('Z3', 'Z1', 'medium', 'push', 'Z5', 'Z5', 'flat')": {
    "slow down": -0.2502991148420309,
    "keep going": -0.24773488330913676,
    "accelerate": 0.0
  },
  "('Z4', 'Z4', 'medium', 'recover', 'Z1', 'Z1', 'uphill')": {
    "slow down": -0.1292990198603788,
    "keep going": 0.0,
    "accelerate": 0.0
  },
  "('Z4', 'Z3', 'medium', 'recover', 'Z1', 'Z1', 'downhill')": {
    "slow down": 33.40912156303448,
    "keep going": -0.07312748153998562,
    "accelerate": -0.09071070151300245
  },
  "('Z2', 'Z4', 'low', 'warmup', 'Z1', 'Z1', 'uphill')": {
    "slow down": -0.07504740042113729,
    "keep going": 0.0,
    "accelerate": 0.0
  },
  "('Z3', 'Z3', 'low', 'warmup', 'Z1', 'Z1', 'flat')": {
    "slow down": 4.47220351024513,
    "keep going": 0.0,
    "accelerate": 0.0
  },
  "('Z5', 'Z5', 'medium', 'recover', 'Z1', 'Z1', 'downhill')": {
    "slow down": -0.2531776909618501,
    "keep going": 0.0,
    "accelerate": 0.0
  },
  "('Z3', 'Z2', 'medium', 'recover', 'Z1', 'Z1', 'uphill')": {
    "slow down": 0.20118339557874979,
    "keep going": 0.0,
    "accelerate": 0.0
  },
  "('Z4', 'Z4', 'medium', 'recover', 'Z1', 'Z1', 'downhill')": {
    "slow down": -0.07348278742991132,
    "keep going": 3.7884566693330477,
    "accelerate": 0.0
  },
  "('Z3', 'Z2', 'medium', 'push', 'Z5', 'Z5', 'uphill')": {
    "slow down": -0.07553738831161026,
    "keep going": 2.2103247791942096,
    "accelerate": 0.0
  },
  "('Z4', 'Z2', 'medium', 'push', 'Z5', 'Z5', 'downhill')": {
    "slow down": -0.23362295649527864,
    "keep going": 0.16581452469609975,
    "accelerate": 0.0
  },
  "('Z4', 'Z5', 'medium', 'recover', 'Z2', 'Z2', 'flat')": {
    "slow down": 26.60554337075248,
    "keep going": 0.4638092191819423,
    "accelerate": 0.0
  },
  "('Z4', 'Z2', 'medium', 'push', 'Z4', 'Z4', 'flat')": {
    "slow down": 15.589645742917174,
    "keep going": 0.0,
    "accelerate": 4.421150914052943
  },
  "('Z2', 'Z2', 'medium', 'recover', 'Z1', 'Z1', 'flat')": {
    "slow down": 45.932210813895985,
    "keep going": 0.0,
    "accelerate": 0.0
  },
  "('Z2', 'Z1', 'medium', 'push', 'Z5', 'Z5', 'flat')": {
    "slow down": -0.27364702451884626,
    "keep going": 0.1066157553417285,
    "accelerate": 0.0
  },
  "('Z3', 'Z3', 'medium', 'push', 'Z5', 'Z5', 'uphill')": {
    "slow down": 1.3598543770727636,
    "keep going": 0.0,
    "accelerate": 0.0
  },
  "('Z2', 'Z2', 'medium', 'recover', 'Z1', 'Z1', 'uphill')": {
    "slow down": 28.534867328195887,
    "keep going": 0.0,
    "accelerate": 0.0
  },
  "('Z5', 'Z4', 'medium', 'push', 'Z5', 'Z5', 'downhill')": {
    "slow down": 31.049858634133308,
    "keep going": 0.0,
    "accelerate": 0.0
  },
  "('Z2', 'Z2', 'medium', 'recover', 'Z1', 'Z1', 'downhill')": {
    "slow down": 21.72215063428602,
    "keep going": 0.0,
    "accelerate": 0.0
  },
  "('Z5', 'Z4', 'low', 'push', 'Z4', 'Z4', 'uphill')": {
    "slow down": 4.385824766207648,
    "keep going": 0.0,
    "accelerate": 0.0
  },
  "('Z4', 'Z2', 'medium', 'push', 'Z5', 'Z5', 'uphill')": {
    "slow down": -0.2456705025872223,
    "keep going": 0.0,
    "accelerate": 0.0
  },
  "('Z3', 'Z3', 'medium', 'push', 'Z4', 'Z4', 'flat')": {
    "slow down": 35.860373575164814,
    "keep going": 0.0,
    "accelerate": 0.0
  },
  "('Z3', 'Z2', 'medium', 'push', 'Z4', 'Z4', 'downhill')": {
    "slow down": 7.073249995008693,
    "keep going": 0.0,
    "accelerate": 0.0
  },
  "('Z3', 'Z3', 'medium', 'push', 'Z4', 'Z4', 'uphill')": {
    "slow down": 11.167571357885953,
    "keep going": 0.0,
    "accelerate": 0.0
  },
  "('Z3', 'Z1', 'medium', 'recover', 'Z2', 'Z2', 'flat')": {
    "slow down": 41.816448388550896,
    "keep going": 5.534366827663879,
    "accelerate": 3.9057592457645507
  },
  "('Z3', 'Z1', 'medium', 'push', 'Z4', 'Z4', 'flat')": {
    "slow down": 25.520607479428563,
    "keep going": 0.0,
    "accelerate": 0.0
  },
  "('Z3', 'Z1', 'medium', 'push', 'Z4', 'Z4', 'uphill')": {
    "slow down": 7.073792348461331,
    "keep going": 0.0,
    "accelerate": 0.0
  },
  "('Z5', 'Z5', 'medium', 'push', 'Z4', 'Z4', 'flat')": {
    "slow down": 42.612201544977495,
    "keep going": 0.0,
    "accelerate": 0.0
  },
  "('Z2', 'Z1', 'medium', 'recover', 'Z2', 'Z2', 'flat')": {
    "slow down": 43.85455396608086,
    "keep going": 17.75462992554177,
    "accelerate": 6.1203569846135
  },
  "('Z5', 'Z5', 'medium', 'push', 'Z4', 'Z4', 'uphill')": {
    "slow down": 21.92017384341824,
    "keep going": 0.0,
    "accelerate": 0.0
  },
  "('Z4', 'Z2', 'low', 'recover', 'Z2', 'Z2', 'flat')": {
    "slow down": 35.50430759549261,
    "keep going": 0.0,
    "accelerate": 0.0
  },
  "('Z2', 'Z1', 'medium', 'push', 'Z4', 'Z4', 'uphill')": {
    "slow down": 7.820916637048243,
    "keep going": 0.0,
    "accelerate": 0.0
  },
  "('Z2', 'Z1', 'medium', 'push', 'Z4', 'Z4', 'flat')": {
    "slow down": 21.321769378742506,
    "keep going": 0.0,
    "accelerate": 0.0
  },
  "('Z3', 'Z3', 'medium', 'recover', 'Z2', 'Z2', 'flat')": {
    "slow down": 14.358343403606701,
    "keep going": 0.0,
    "accelerate": 0.0
  },
  "('Z3', 'Z2', 'medium', 'push', 'Z4', 'Z4', 'uphill')": {
    "slow down": 2.015507226086326,
    "keep going": 0.0,
    "accelerate": 0.0
  },
  "('Z2', 'Z2', 'medium', 'recover', 'Z2', 'Z2', 'flat')": {
    "slow down": 12.221856079931479,
    "keep going": 0.0,
    "accelerate": 0.0
  },
  "('Z4', 'Z2', 'medium', 'recover', 'Z2', 'Z2', 'flat')": {
    "slow down": 11.332650996693708,
    "keep going": 0.0,
    "accelerate": 0.0
  }
}